mansel.py
mansel_lib-0.1.0.dist-info/LICENSE.txt
mansel_lib-0.1.0.dist-info/METADATA
mansel_lib-0.1.0.dist-info/WHEEL
mansel_lib-0.1.0.dist-info/top_level.txt
mansel_lib-0.1.0.dist-info/RECORD
