Metadata-Version: 2.1
Name: mansel-lib
Version: 0.1.0
Summary: Library for manual file selection
Home-page: https://github.com/willsALMANJ/mansel
Author: https://github.com/willsALMANJ
Author-email: wsha.code@gmail.com
License: UNKNOWN
Platform: UNKNOWN
Classifier: Programming Language :: Python :: 3
Classifier: License :: OSI Approved :: BSD License
Classifier: Operating System :: OS Independent
Classifier: Environment :: X11 Applications :: Qt
